LICENSE.txt
setup.py
Topsis_yash_101903780.egg-info/PKG-INFO
Topsis_yash_101903780.egg-info/SOURCES.txt
Topsis_yash_101903780.egg-info/dependency_links.txt
Topsis_yash_101903780.egg-info/requires.txt
Topsis_yash_101903780.egg-info/top_level.txt
topsis/__init__.py
topsis/topsis_101903780.py