Metadata-Version: 2.1
Name: Topsis-yash-101903780
Version: 0.0.2
Summary: A Python package to find TOPSIS for multi-criteria decision analysis method
Home-page: https://github.com/YashKumar-0307/topsis/archive/refs/tags/0.0.2.tar.gz
Author: Yash Kumar
Author-email: ykumar1_be19@thapar.edu
License: MIT
Keywords: topsis,UCS654,101903780
Platform: UNKNOWN
Classifier: Development Status :: 3 - Alpha
Classifier: Intended Audience :: Developers
Classifier: Operating System :: Microsoft :: Windows :: Windows 10
Classifier: License :: OSI Approved :: MIT License
Classifier: Programming Language :: Python :: 3
License-File: LICENSE.txt
